cisco_hashgen/__init__.py
cisco_hashgen/__main__.py
cisco_hashgen/cli.py
cisco_hashgen-2.0.1.dist-info/licenses/LICENSE
cisco_hashgen-2.0.1.dist-info/METADATA
cisco_hashgen-2.0.1.dist-info/WHEEL
cisco_hashgen-2.0.1.dist-info/entry_points.txt
cisco_hashgen-2.0.1.dist-info/top_level.txt
cisco_hashgen-2.0.1.dist-info/RECORD
