Metadata-Version: 2.4
Name: cisco-hashgen
Version: 2.0.1
Summary: Generate and verify Cisco-compatible password hashes for Cisco ASA & IOS/IOS-XE.
Author: Gilbert Mendoza
License-Expression: MIT
Project-URL: Homepage, https://github.com/Krontab/cisco-hashgen
Project-URL: Issues, https://github.com/Krontab/cisco-hashgen/issues
Keywords: Cisco,ASA,IOS,PBKDF2,password,security,networking,router,switch,firewall
Classifier: Programming Language :: Python :: 3.9
Classifier: Programming Language :: Python :: 3.10
Classifier: Programming Language :: Python :: 3.11
Classifier: Programming Language :: Python :: 3.12
Classifier: Programming Language :: Python :: 3.13
Classifier: Environment :: Console
Classifier: Topic :: Security :: Cryptography
Classifier: Topic :: System :: Systems Administration
Requires-Python: >=3.8
License-File: LICENSE
Provides-Extra: dev
Requires-Dist: build; extra == "dev"
Requires-Dist: twine; extra == "dev"
Requires-Dist: pipx; extra == "dev"
Dynamic: license-file
